Workbook

Sheet Readme
A1: Notes:
A2: 2026-10-23 (review response A2): calibration!D2 and calibrationUS!D2 are public cash spending on old-age and survivors pensions in 2020, 7.836% of GDP, OECD SOCX (OECD.ELS.SPD:DSD_SOCX_AGG, public ES10, old age and survivors TP01, in cash C, % of GDP; retrieved 2026-09-30), the value in data/oecdFigure1.csv column pensionSpending (figure 1.1), over the labour share 1-B2. They were =0.083/(1-B2), SOCX cash plus in kind (8.269).

Sheet population
A1: t | B1: Worker-to-retiree (census) | C1: Worker-to-retiree
A2: =A3-30 -> 1960 | B2: 3.8333171 | C2: 1.0919194
A3: =A4-30 -> 1990 | B3: 3.5524059 | C3: 1.0919194
A4: 2020 | B4: 3.0010999 | C4: 1.1740347
A5: =A4+30 -> 2050 | B5: 2.6876031 | C5: 1.1210482
A6: =A5+30 -> 2080 | B6: 2.5949773 | C6: 1.0059807
A7: =A6+30 -> 2110 | B7: 2.5949773 | C7: 1.0059807

Sheet heterogeneity
A1: Group | B1: CumPopShares | C1: Population shares | D1: Hours | E1: Income | F1: Voting shares | G1: Survival rate | H1: Replacement rate
A2: 0 | B2: =C2 -> 0 | C2: 0 | D2: 1 | E2: 1 | F2: 1 | G2: 1 | H2: 0
A3: 1 | B3: =B2+C3 -> 0.29163249 | C3: =711/(711+1417+310) -> 0.29163249 | D3: 1693.7 | E3: 14087 | F3: 0.6064477 | G3: 1 | H3: 70.6
A4: 2 | B4: =B3+C4 -> 0.8728466 | C4: =1417/(711+1417+310) -> 0.58121411 | D4: 1846.87 | E4: 28201 | F4: 0.6993464 | G4: 1 | H4: 49
A5: 3 | B5: =B4+C5 -> 1 | C5: =310/(711+1417+310) -> 0.1271534 | D5: 1875.13 | E5: 60319 | F5: 0.7352941 | G5: 1 | H5: =38.2+(49-38.2)*(1-E5/(2*E4)) -> 37.449963

Sheet heterogeneityUS
A1: Group | B1: CumPopShares | C1: Population shares | D1: Hours | E1: Income | F1: Voting shares | G1: Survival rate | H1: Replacement rate
A2: 0 | B2: =C2 -> 0 | C2: 0 | D2: 1 | E2: 1 | F2: 1 | G2: 1
A3: 1 | B3: =B2+C3 -> 0.58226607 | C3: =18413/(18413+5557+7653) -> 0.58226607 | D3: =FORECAST($B3,heterogeneity!D$3:D$5,heterogeneity!$B$3:$B$5) -> 1769.2558 | E3: =FORECAST($B3,heterogeneity!E$3:E$5,heterogeneity!$B$3:$B$5) -> 26875.202 | F3: =FORECAST($B3,heterogeneity!F$3:F$5,heterogeneity!$B$3:$B$5) -> 0.65598547 | G3: =FORECAST($B3,heterogeneity!G$3:G$5,heterogeneity!$B$3:$B$5) -> 1 | H3: =FORECAST($B3,heterogeneity!H$3:H$5,heterogeneity!$B$3:$B$5) -> 58.451849
A4: 2 | B4: =B3+C4 -> 0.7579926 | C4: =5557/(18413+5557+7653) -> 0.17572653 | D4: =FORECAST($B4,heterogeneity!D$3:D$5,heterogeneity!$B$3:$B$5) -> 1814.6652 | E4: =FORECAST($B4,heterogeneity!E$3:E$5,heterogeneity!$B$3:$B$5) -> 36123.205 | F4: =FORECAST($B4,heterogeneity!F$3:F$5,heterogeneity!$B$3:$B$5) -> 0.68675345 | G4: =FORECAST($B4,heterogeneity!G$3:G$5,heterogeneity!$B$3:$B$5) -> 1 | H4: =FORECAST($B4,heterogeneity!H$3:H$5,heterogeneity!$B$3:$B$5) -> 50.750331
A5: 3 | B5: =B4+C5 -> 1 | C5: =7653/(18413+5557+7653) -> 0.2420074 | D5: =FORECAST($B5,heterogeneity!D$3:D$5,heterogeneity!$B$3:$B$5) -> 1877.2022 | E5: =FORECAST($B5,heterogeneity!E$3:E$5,heterogeneity!$B$3:$B$5) -> 48859.388 | F5: =FORECAST($B5,heterogeneity!F$3:F$5,heterogeneity!$B$3:$B$5) -> 0.72912655 | G5: =FORECAST($B5,heterogeneity!G$3:G$5,heterogeneity!$B$3:$B$5) -> 1 | H5: =FORECAST($B5,heterogeneity!H$3:H$5,heterogeneity!$B$3:$B$5) -> 40.143939

Sheet calibration
A1: Calibration year | B1: Capital income share | C1: Labor supply elasticity | D1: Pension tax | E1: Universal share | F1: Replacement rate | G1: Replacement rate groups | H1: Average workweek
A2: 2020 | B2: 0.3 | C2: 0.3 | D2: =0.07836/(1-B2) -> 0.11194286 | E2: 0 | F2: =heterogeneity!H4/heterogeneity!H3 -> 0.69405099 | G2: [1,2] | H2: =SUMPRODUCT(heterogeneity!C3:C5,heterogeneity!D3:D5)/52 -> 34.726808

Sheet calibrationUS
A1: Calibration year | B1: Capital income share | C1: Labor supply elasticity | D1: Pension tax | E1: Universal share | F1: Replacement rate | G1: Replacement rate groups | H1: Average workweek
A2: 2020 | B2: 0.3 | C2: 0.3 | D2: =0.07836/(1-B2) -> 0.11194286 | E2: 0 | F2: =heterogeneityUS!H4/heterogeneityUS!H3 -> 0.86824167 | G2: [1,2] | H2: =SUMPRODUCT(heterogeneityUS!C3:C5,heterogeneityUS!D3:D5)/52 -> 34.679985
